starmerxauth/__init__.py
starmerxauth/middleware.py
starmerxauth-0.3.3.dist-info/METADATA
starmerxauth-0.3.3.dist-info/WHEEL
starmerxauth-0.3.3.dist-info/top_level.txt
starmerxauth-0.3.3.dist-info/zip-safe
starmerxauth-0.3.3.dist-info/RECORD
