Metadata-Version: 2.1
Name: starmerxauth
Version: 0.3.3
Summary: starmerx verify jwt
Home-page: UNKNOWN
Author: yang
Author-email: yangjuan@starmerx.com
License: MIT
Platform: UNKNOWN
Classifier: Environment :: Web Environment
Classifier: Intended Audience :: Developers
Classifier: Natural Language :: English
Classifier: Operating System :: Unix
Classifier: Topic :: Software Development :: Libraries :: Python Modules
Classifier: Programming Language :: Python
Requires-Dist: PyJWT (==1.7.1)
Requires-Dist: cryptography (!=3.3,<=3.3.2,>=2.7)
